README.rst
setup.py
scripts/rosco
scripts/rosinstall
scripts/roslocate
scripts/rosws
src/rosinstall/__init__.py
src/rosinstall/__version__.py
src/rosinstall/distro_locate.py
src/rosinstall/helpers.py
src/rosinstall/locate.py
src/rosinstall/rosinstall_cli.py
src/rosinstall/rosinstall_cmd.py
src/rosinstall/rosws_cli.py
src/rosinstall/rosws_stacks_cli.py
src/rosinstall/setupfiles.py
src/rosinstall/simple_checkout.py
src/rosinstall.egg-info/PKG-INFO
src/rosinstall.egg-info/SOURCES.txt
src/rosinstall.egg-info/dependency_links.txt
src/rosinstall.egg-info/requires.txt
src/rosinstall.egg-info/top_level.txt